Workbook

Sheet Inputs
A1: parameter | B1: value
A2: local_rent_monthly | B2: 80000
A3: utilities_monthly | B3: 10000
A4: social_support_salary_monthly | B4: 50000
A5: hosting_monthly | B5: 18000
A6: sales_specialist_fixed_monthly | B6: 60000
A7: developer_salary_monthly | B7: 0
A8: flutterwave_pct | B8: 0.03
A9: CAC | B9: 10000
A10: churn_monthly_pct | B10: 0.05
A11: avg_lifetime_months | B11: =1/Inputs!B9 -> 0.0001
A12: solo_price | B12: 8000
A13: basic_price | B13: 35000
A14: pro_price | B14: 65000
A15: solo_count | B15: 20
A16: basic_count | B16: 20
A17: pro_count | B17: 10
A18: solo_storage_gb | B18: 1
A19: basic_storage_gb | B19: 3
A20: pro_storage_gb | B20: 5
A21: commission_rate | B21: 0.2
A22: initial_clients_m1 | B22: 10
A23: initial_clients_m2 | B23: 30
... A32: usd_to_xaf | B32: 600
A33: wasabi_cost_per_gb_xaf | B33: =B31*B32 -> 3.54

Sheet Totals
A1: fixed_costs_total | B1: =SUM(Inputs!B2:'Inputs'!B6) -> 218000
A2: storage_cost_monthly (Wasabi XAF) | B2: =SUM(Projections!V2:V13) -> 2870
A3: MRR_total_month | B3: =SUM(Projections!H2:H13) -> 37310000
A4: flutterwave_fees_total_month | B4: =SUM(Projections!J2:J13) -> 1344300
A5: commission_total_month | B5: =SUM(Projections!M2:M13) -> 8962000
A6: profit_before_commissions_month_total | B6: =SUM(Projections!P2:P13) -> 28236830
A7: profit_after_commissions_month_total | B7: =SUM(Projections!Q2:Q13) -> 214435000
A8: archive_revenue_month | B8: =Projections!I5 -> 625000

Sheet Plans
A1: plan | B1: price_per_month | C1: clients_current | D1: revenue_current | E1: storage_gb_included
A2: Solo | B2: =Inputs!B12 -> 8000 | E2: =Inputs!B18 -> 1
A3: Basic | B3: =Inputs!B13 -> 35000 | E3: =Inputs!B19 -> 3
A4: Pro | B4: =Inputs!B14 -> 65000 | E4: =Inputs!B20 -> 5

Sheet Projections
A1: Month | B1: NewClients | C1: ChurnClients | D1: TotalClients | E1: SoloClients | F1: BasicClients | G1: ProClients | H1: MRR | I1: ArchiveRevenue | J1: FlutterwaveFees | K1: CommissionSubscriptions | L1: CommissionArchive | M1: CommissionTotal | N1: ArchiveCost | O1: ProfitBeforeCommission | P1: ProfitAfterCommission | Q1: CumulativeMRR | R1: CumulativeCommission | S1: SoloStorageGB | T1: BasicStorageGB | U1: ProStorageGB | V1: TotalStorageGB | W1: StorageCostWasabiXAF
A2: M1 | B2: =Inputs!B22 -> 10 | C2: =0 -> 0 | D2: =B2 - C2 -> 10 | G2: =D2 - E2 - F2 -> 10 | H2: =E2*Inputs!B12 + F2*Inputs!B13 + G2*Inputs!B14 -> 650000 | I2: =Inputs!B30 * Inputs!B27 -> 625000 | J2: =ROUND((H2 + I2) * Inputs!B8,0) -> 38250 | K2: =ROUND(H2 * Inputs!B21,0) -> 130000 | L2: =ROUND(I2 * Inputs!B21,0) -> 125000 | M2: =K2 + L2 -> 255000 | N2: =Inputs!B30 * Inputs!B26 -> 304000 | O2: =(H2 + I2) - (Totals!$B$1 + J2 + N2 + V2) -> 714700 | P2: =O2 - M2 -> 459700 | Q2: =H2 -> 650000 | R2: =M2 -> 255000 | S2: =E2 * Inputs!$B$18 -> 0 | T2: =F2 * Inputs!$B$19 -> 0 | U2: =G2 * Inputs!$B$20 -> 50 | V2: =SUM(S2:U2) -> 50 | W2: =ROUND(V2 * Inputs!$B$33,0) -> 177
A3: M2 | B3: =Inputs!B23 - Projections!D2 -> 20 | C3: =ROUND(Projections!D2 * Inputs!B10,0) -> 1 | D3: =Projections!D2 + B3 - C3 -> 29 | G3: =D3 - E3 - F3 -> 29 | H3: =E3*Inputs!B12 + F3*Inputs!B13 + G3*Inputs!B14 -> 1885000 | I3: =Inputs!B30 * Inputs!B27 -> 625000 | J3: =ROUND((H3 + I3) * Inputs!B8,0) -> 75300 | K3: =ROUND(H3 * Inputs!B21,0) -> 377000 | L3: =ROUND(I3 * Inputs!B21,0) -> 125000 | M3: =K3 + L3 -> 502000 | N3: =Inputs!B30 * Inputs!B26 -> 304000 | O3: =(H3 + I3) - (Totals!$B$1 + J3 + N3 + V3) -> 1912555 | P3: =O3 - M3 -> 1410555 | Q3: =Q2 + H3 -> 2535000 | R3: =R2 + M3 -> 757000 | S3: =E3 * Inputs!$B$18 -> 0 | T3: =F3 * Inputs!$B$19 -> 0 | U3: =G3 * Inputs!$B$20 -> 145 | V3: =SUM(S3:U3) -> 145 | W3: =ROUND(V3 * Inputs!$B$33,0) -> 513
A4: M3 | B4: =Inputs!B24 - Projections!D3 -> 21 | C4: =ROUND(Projections!D3 * Inputs!B10,0) -> 1 | D4: =Projections!D3 + B4 - C4 -> 49 | G4: =D4 - E4 - F4 -> 49 | H4: =E4*Inputs!B12 + F4*Inputs!B13 + G4*Inputs!B14 -> 3185000 | I4: =Inputs!B30 * Inputs!B27 -> 625000 | J4: =ROUND((H4 + I4) * Inputs!B8,0) -> 114300 | K4: =ROUND(H4 * Inputs!B21,0) -> 637000 | L4: =ROUND(I4 * Inputs!B21,0) -> 125000 | M4: =K4 + L4 -> 762000 | N4: =Inputs!B30 * Inputs!B26 -> 304000 | O4: =(H4 + I4) - (Totals!$B$1 + J4 + N4 + V4) -> 3173455 | P4: =O4 - M4 -> 2411455 | Q4: =Q3 + H4 -> 5720000 | R4: =R3 + M4 -> 1519000 | S4: =E4 * Inputs!$B$18 -> 0 | T4: =F4 * Inputs!$B$19 -> 0 | U4: =G4 * Inputs!$B$20 -> 245 | V4: =SUM(S4:U4) -> 245 | W4: =ROUND(V4 * Inputs!$B$33,0) -> 867
A5: M4 | B5: =ROUND(Projections!D4 * Inputs!B25,0) -> 3 | C5: =ROUND(Projections!D4 * Inputs!B10,0) -> 2 | D5: =Projections!D4 + B5 - C5 -> 50 | G5: =D5 - E5 - F5 -> 50 | H5: =E5*Inputs!B12 + F5*Inputs!B13 + G5*Inputs!B14 -> 3250000 | I5: =Inputs!B30 * Inputs!B27 -> 625000 | J5: =ROUND((H5 + I5) * Inputs!B8,0) -> 116250 | K5: =ROUND(H5 * Inputs!B21,0) -> 650000 | L5: =ROUND(I5 * Inputs!B21,0) -> 125000 | M5: =K5 + L5 -> 775000 | N5: =Inputs!B30 * Inputs!B26 -> 304000 | O5: =(H5 + I5) - (Totals!$B$1 + J5 + N5 + V5) -> 3236500 | P5: =O5 - M5 -> 2461500 | Q5: =Q4 + H5 -> 8970000 | R5: =R4 + M5 -> 2294000 | S5: =E5 * Inputs!$B$18 -> 0 | T5: =F5 * Inputs!$B$19 -> 0 | U5: =G5 * Inputs!$B$20 -> 250 | V5: =SUM(S5:U5) -> 250 | W5: =ROUND(V5 * Inputs!$B$33,0) -> 885
A6: M5 | B6: =ROUND(Projections!D5 * Inputs!B25,0) -> 4 | C6: =ROUND(Projections!D5 * Inputs!B10,0) -> 3 | D6: =Projections!D5 + B6 - C6 -> 51 | G6: =D6 - E6 - F6 -> 51 | H6: =E6*Inputs!B12 + F6*Inputs!B13 + G6*Inputs!B14 -> 3315000 | I6: =Inputs!B30 * Inputs!B27 -> 625000 | J6: =ROUND((H6 + I6) * Inputs!B8,0) -> 118200 | K6: =ROUND(H6 * Inputs!B21,0) -> 663000 | L6: =ROUND(I6 * Inputs!B21,0) -> 125000 | M6: =K6 + L6 -> 788000 | N6: =Inputs!B30 * Inputs!B26 -> 304000 | O6: =(H6 + I6) - (Totals!$B$1 + J6 + N6 + V6) -> 3299545 | P6: =O6 - M6 -> 2511545 | Q6: =Q5 + H6 -> 12285000 | R6: =R5 + M6 -> 3082000 | S6: =E6 * Inputs!$B$18 -> 0 | T6: =F6 * Inputs!$B$19 -> 0 | U6: =G6 * Inputs!$B$20 -> 255 | V6: =SUM(S6:U6) -> 255 | W6: =ROUND(V6 * Inputs!$B$33,0) -> 903
A7: M6 | B7: =ROUND(Projections!D6 * Inputs!B25,0) -> 4 | C7: =ROUND(Projections!D6 * Inputs!B10,0) -> 3 | D7: =Projections!D6 + B7 - C7 -> 52 | G7: =D7 - E7 - F7 -> 52 | H7: =E7*Inputs!B12 + F7*Inputs!B13 + G7*Inputs!B14 -> 3380000 | I7: =Inputs!B30 * Inputs!B27 -> 625000 | J7: =ROUND((H7 + I7) * Inputs!B8,0) -> 120150 | K7: =ROUND(H7 * Inputs!B21,0) -> 676000 | L7: =ROUND(I7 * Inputs!B21,0) -> 125000 | M7: =K7 + L7 -> 801000 | N7: =Inputs!B30 * Inputs!B26 -> 304000 | O7: =(H7 + I7) - (Totals!$B$1 + J7 + N7 + V7) -> 3362590 | P7: =O7 - M7 -> 2561590 | Q7: =Q6 + H7 -> 15665000 | R7: =R6 + M7 -> 3883000 | S7: =E7 * Inputs!$B$18 -> 0 | T7: =F7 * Inputs!$B$19 -> 0 | U7: =G7 * Inputs!$B$20 -> 260 | V7: =SUM(S7:U7) -> 260 | W7: =ROUND(V7 * Inputs!$B$33,0) -> 920
A8: M7 | B8: =ROUND(Projections!D7 * Inputs!B25,0) -> 4 | C8: =ROUND(Projections!D7 * Inputs!B10,0) -> 3 | D8: =Projections!D7 + B8 - C8 -> 53 | G8: =D8 - E8 - F8 -> 53 | H8: =E8*Inputs!B12 + F8*Inputs!B13 + G8*Inputs!B14 -> 3445000 | I8: =Inputs!B30 * Inputs!B27 -> 625000 | J8: =ROUND((H8 + I8) * Inputs!B8,0) -> 122100 | K8: =ROUND(H8 * Inputs!B21,0) -> 689000 | L8: =ROUND(I8 * Inputs!B21,0) -> 125000 | M8: =K8 + L8 -> 814000 | N8: =Inputs!B30 * Inputs!B26 -> 304000 | O8: =(H8 + I8) - (Totals!$B$1 + J8 + N8 + V8) -> 3425635 | P8: =O8 - M8 -> 2611635 | Q8: =Q7 + H8 -> 19110000 | R8: =R7 + M8 -> 4697000 | S8: =E8 * Inputs!$B$18 -> 0 | T8: =F8 * Inputs!$B$19 -> 0 | U8: =G8 * Inputs!$B$20 -> 265 | V8: =SUM(S8:U8) -> 265 | W8: =ROUND(V8 * Inputs!$B$33,0) -> 938
A9: M8 | B9: =ROUND(Projections!D8 * Inputs!B25,0) -> 4 | C9: =ROUND(Projections!D8 * Inputs!B10,0) -> 3 | D9: =Projections!D8 + B9 - C9 -> 54 | G9: =D9 - E9 - F9 -> 54 | H9: =E9*Inputs!B12 + F9*Inputs!B13 + G9*Inputs!B14 -> 3510000 | I9: =Inputs!B30 * Inputs!B27 -> 625000 | J9: =ROUND((H9 + I9) * Inputs!B8,0) -> 124050 | K9: =ROUND(H9 * Inputs!B21,0) -> 702000 | L9: =ROUND(I9 * Inputs!B21,0) -> 125000 | M9: =K9 + L9 -> 827000 | N9: =Inputs!B30 * Inputs!B26 -> 304000 | O9: =(H9 + I9) - (Totals!$B$1 + J9 + N9 + V9) -> 3488680 | P9: =O9 - M9 -> 2661680 | Q9: =Q8 + H9 -> 22620000 | R9: =R8 + M9 -> 5524000 | S9: =E9 * Inputs!$B$18 -> 0 | T9: =F9 * Inputs!$B$19 -> 0 | U9: =G9 * Inputs!$B$20 -> 270 | V9: =SUM(S9:U9) -> 270 | W9: =ROUND(V9 * Inputs!$B$33,0) -> 956
A10: M9 | B10: =ROUND(Projections!D9 * Inputs!B25,0) -> 4 | C10: =ROUND(Projections!D9 * Inputs!B10,0) -> 3 | D10: =Projections!D9 + B10 - C10 -> 55 | G10: =D10 - E10 - F10 -> 55 | H10: =E10*Inputs!B12 + F10*Inputs!B13 + G10*Inputs!B14 -> 3575000 | I10: =Inputs!B30 * Inputs!B27 -> 625000 | J10: =ROUND((H10 + I10) * Inputs!B8,0) -> 126000 | K10: =ROUND(H10 * Inputs!B21,0) -> 715000 | L10: =ROUND(I10 * Inputs!B21,0) -> 125000 | M10: =K10 + L10 -> 840000 | N10: =Inputs!B30 * Inputs!B26 -> 304000 | O10: =(H10 + I10) - (Totals!$B$1 + J10 + N10 + V10) -> 3551725 | P10: =O10 - M10 -> 2711725 | Q10: =Q9 + H10 -> 26195000 | R10: =R9 + M10 -> 6364000 | S10: =E10 * Inputs!$B$18 -> 0 | T10: =F10 * Inputs!$B$19 -> 0 | U10: =G10 * Inputs!$B$20 -> 275 | V10: =SUM(S10:U10) -> 275 | W10: =ROUND(V10 * Inputs!$B$33,0) -> 974
A11: M10 | B11: =ROUND(Projections!D10 * Inputs!B25,0) -> 4 | C11: =ROUND(Projections!D10 * Inputs!B10,0) -> 3 | D11: =Projections!D10 + B11 - C11 -> 56 | G11: =D11 - E11 - F11 -> 56 | H11: =E11*Inputs!B12 + F11*Inputs!B13 + G11*Inputs!B14 -> 3640000 | I11: =Inputs!B30 * Inputs!B27 -> 625000 | J11: =ROUND((H11 + I11) * Inputs!B8,0) -> 127950 | K11: =ROUND(H11 * Inputs!B21,0) -> 728000 | L11: =ROUND(I11 * Inputs!B21,0) -> 125000 | M11: =K11 + L11 -> 853000 | N11: =Inputs!B30 * Inputs!B26 -> 304000 | O11: =(H11 + I11) - (Totals!$B$1 + J11 + N11 + V11) -> 3614770 | P11: =O11 - M11 -> 2761770 | Q11: =Q10 + H11 -> 29835000 | R11: =R10 + M11 -> 7217000 | S11: =E11 * Inputs!$B$18 -> 0 | T11: =F11 * Inputs!$B$19 -> 0 | U11: =G11 * Inputs!$B$20 -> 280 | V11: =SUM(S11:U11) -> 280 | W11: =ROUND(V11 * Inputs!$B$33,0) -> 991
A12: M11 | B12: =ROUND(Projections!D11 * Inputs!B25,0) -> 4 | C12: =ROUND(Projections!D11 * Inputs!B10,0) -> 3 | D12: =Projections!D11 + B12 - C12 -> 57 | G12: =D12 - E12 - F12 -> 57 | H12: =E12*Inputs!B12 + F12*Inputs!B13 + G12*Inputs!B14 -> 3705000 | I12: =Inputs!B30 * Inputs!B27 -> 625000 | J12: =ROUND((H12 + I12) * Inputs!B8,0) -> 129900 | K12: =ROUND(H12 * Inputs!B21,0) -> 741000 | L12: =ROUND(I12 * Inputs!B21,0) -> 125000 | M12: =K12 + L12 -> 866000 | N12: =Inputs!B30 * Inputs!B26 -> 304000 | O12: =(H12 + I12) - (Totals!$B$1 + J12 + N12 + V12) -> 3677815 | P12: =O12 - M12 -> 2811815 | Q12: =Q11 + H12 -> 33540000 | R12: =R11 + M12 -> 8083000 | S12: =E12 * Inputs!$B$18 -> 0 | T12: =F12 * Inputs!$B$19 -> 0 | U12: =G12 * Inputs!$B$20 -> 285 | V12: =SUM(S12:U12) -> 285 | W12: =ROUND(V12 * Inputs!$B$33,0) -> 1009
A13: M12 | B13: =ROUND(Projections!D12 * Inputs!B25,0) -> 4 | C13: =ROUND(Projections!D12 * Inputs!B10,0) -> 3 | D13: =Projections!D12 + B13 - C13 -> 58 | G13: =D13 - E13 - F13 -> 58 | H13: =E13*Inputs!B12 + F13*Inputs!B13 + G13*Inputs!B14 -> 3770000 | I13: =Inputs!B30 * Inputs!B27 -> 625000 | J13: =ROUND((H13 + I13) * Inputs!B8,0) -> 131850 | K13: =ROUND(H13 * Inputs!B21,0) -> 754000 | L13: =ROUND(I13 * Inputs!B21,0) -> 125000 | M13: =K13 + L13 -> 879000 | N13: =Inputs!B30 * Inputs!B26 -> 304000 | O13: =(H13 + I13) - (Totals!$B$1 + J13 + N13 + V13) -> 3740860 | P13: =O13 - M13 -> 2861860 | Q13: =Q12 + H13 -> 37310000 | R13: =R12 + M13 -> 8962000 | S13: =E13 * Inputs!$B$18 -> 0 | T13: =F13 * Inputs!$B$19 -> 0 | U13: =G13 * Inputs!$B$20 -> 290 | V13: =SUM(S13:U13) -> 290 | W13: =ROUND(V13 * Inputs!$B$33,0) -> 1027

Sheet Charts
A1: Month | B1: ChurnRate
A2: M1 | B2: =0 -> 0
A3: M2 | B3: =IF(Projections!D2>0, Projections!C3 / Projections!D2, 0) -> 0.1
A4: M3 | B4: =IF(Projections!D3>0, Projections!C4 / Projections!D3, 0) -> 0.034482759
A5: M4 | B5: =IF(Projections!D4>0, Projections!C5 / Projections!D4, 0) -> 0.040816327
A6: M5 | B6: =IF(Projections!D5>0, Projections!C6 / Projections!D5, 0) -> 0.06
A7: M6 | B7: =IF(Projections!D6>0, Projections!C7 / Projections!D6, 0) -> 0.058823529
A8: M7 | B8: =IF(Projections!D7>0, Projections!C8 / Projections!D7, 0) -> 0.057692308
A9: M8 | B9: =IF(Projections!D8>0, Projections!C9 / Projections!D8, 0) -> 0.056603774
A10: M9 | B10: =IF(Projections!D9>0, Projections!C10 / Projections!D9, 0) -> 0.055555556
A11: M10 | B11: =IF(Projections!D10>0, Projections!C11 / Projections!D10, 0) -> 0.054545455
A12: M11 | B12: =IF(Projections!D11>0, Projections!C12 / Projections!D11, 0) -> 0.053571429
A13: M12 | B13: =IF(Projections!D12>0, Projections!C13 / Projections!D12, 0) -> 0.052631579
